README.md
lolviz.py
setup.cfg
setup.py
lolviz.egg-info/PKG-INFO
lolviz.egg-info/SOURCES.txt
lolviz.egg-info/dependency_links.txt
lolviz.egg-info/requires.txt
lolviz.egg-info/top_level.txt