Metadata-Version: 1.1
Name: lolviz
Version: 1.3.2
Summary: A simple Python data-structure visualization tool for lists of lists, lists, dictionaries
Home-page: https://github.com/parrt/lolviz
Author: Terence Parr
Author-email: parrt@antlr.org
License: BSD
Keywords: visualization data structures
Platform: UNKNOWN
Classifier: License :: OSI Approved :: BSD License
Classifier: Intended Audience :: Developers
